indent_template/__init__.py
indent_template/test.py
indent_template-0.0.2.dist-info/METADATA
indent_template-0.0.2.dist-info/WHEEL
indent_template-0.0.2.dist-info/top_level.txt
indent_template-0.0.2.dist-info/RECORD
