Metadata-Version: 2.1
Name: indent-template
Version: 0.0.2
Summary: A tool to replace strings without breaking indent.
Home-page: https://github.co.jp/
Author: bib_inf
Author-email: contact.bibinf@gmail.com
License: CC0 v1.0
Classifier: Programming Language :: Python :: 3
Classifier: License :: CC0 1.0 Universal (CC0 1.0) Public Domain Dedication
Requires-Dist: ezpip
Requires-Dist: relpath
Requires-Dist: sout
